twbm/__init__.py
twbm/bookmarks.py
twbm/buku.py
twbm/environment.py
twbm/handle_uri.py
twbm/sql.py
twbm/twb.py
twbm/db/__init__.py
twbm/db/dal.py
twbm-0.17.4.data/scripts/twbm-downgrade-db.sh
twbm-0.17.4.data/scripts/twbm-upgrade-db.sh
twbm-0.17.4.dist-info/LICENSE
twbm-0.17.4.dist-info/METADATA
twbm-0.17.4.dist-info/WHEEL
twbm-0.17.4.dist-info/entry_points.txt
twbm-0.17.4.dist-info/top_level.txt
twbm-0.17.4.dist-info/RECORD
