Metadata-Version: 2.1
Name: twbm
Version: 0.17.4
Summary: "CLI bookmark buddy"
Home-page: https://github.com/sysid/twbm
Author: sysid
Author-email: sysid@gmx.de
Classifier: Development Status :: 4 - Beta
Classifier: Environment :: Console
Classifier: Intended Audience :: Developers
Classifier: License :: OSI Approved :: GNU General Public License v3 (GPLv3)
Classifier: Operating System :: OS Independent
Classifier: Topic :: Utilities
Classifier: Programming Language :: Python :: 3
Classifier: Programming Language :: Python :: 3.10
Requires-Python: >=3.10
License-File: LICENSE
Requires-Dist: beautifulsoup4
Requires-Dist: certifi
Requires-Dist: cryptography
Requires-Dist: urllib3
Requires-Dist: html5lib
Requires-Dist: aiosql
Requires-Dist: SQLAlchemy
Requires-Dist: alembic
Requires-Dist: typer
Requires-Dist: pydantic[dotenv]
